MANIFEST.in
requirements.txt
setup.py
test_requirements.txt
version.txt
cloudshell/__init__.py
cloudshell/traffic/__init__.py
cloudshell/traffic/teravm/__init__.py
cloudshell/traffic/teravm/vchassis/__init__.py
cloudshell/traffic/teravm/vchassis/configuration_attributes_structure.py
cloudshell/traffic/teravm/vchassis/flows/__init__.py
cloudshell/traffic/teravm/vchassis/flows/configure_license_server_flow.py
cloudshell/traffic/teravm/vchassis/runners/__init__.py
cloudshell/traffic/teravm/vchassis/runners/configuration_runner.py
cloudshell_tg_teravm_vchassis.egg-info/PKG-INFO
cloudshell_tg_teravm_vchassis.egg-info/SOURCES.txt
cloudshell_tg_teravm_vchassis.egg-info/dependency_links.txt
cloudshell_tg_teravm_vchassis.egg-info/requires.txt
cloudshell_tg_teravm_vchassis.egg-info/top_level.txt